jdatetime/__init__.py
jdatetime-5.1.1.dist-info/LICENSE
jdatetime-5.1.1.dist-info/METADATA
jdatetime-5.1.1.dist-info/WHEEL
jdatetime-5.1.1.dist-info/top_level.txt
jdatetime-5.1.1.dist-info/RECORD
